LISCENSE
MANIFEST.in
README.rst
requirements.txt
setup.py
bin/lobot
lobot/__init__.py
lobot/lobot.py
lobot/plugin_manager.py
lobot.egg-info/PKG-INFO
lobot.egg-info/SOURCES.txt
lobot.egg-info/dependency_links.txt
lobot.egg-info/top_level.txt
lobot/irc/__init__.py
lobot/irc/message.py
lobot/irc/protocol.py
lobot/irc/rfc.py
lobot/plugins/__init__.py
lobot/plugins/catfacts.py
lobot/plugins/http.py
lobot/plugins/plugin.py
lobot/plugins/tell.py