Metadata-Version: 1.1
Name: lobot
Version: 0.0.7
Summary: An extensible IRC bot
Home-page: https://github.com/pyrated/lobot
Author: Scott LaVigne
Author-email: pyrated@gmail.com
License: MIT
Download-URL: https://github.com/pyrated/lobot.git
Platform: UNKNOWN
Classifier: Development Status :: 3 - Alpha
Classifier: License :: OSI Approved :: MIT License
Classifier: Environment :: Console
Classifier: Programming Language :: Python :: 3.5
